Adlib/__init__.py
Adlib/analiseDocumentos.py
Adlib/api.py
Adlib/apiConferirRg.py
Adlib/apiValid.py
Adlib/blip.py
Adlib/confirmacao.py
Adlib/criacao.py
Adlib/enums.py
Adlib/exceptions.py
Adlib/fluxguard.py
Adlib/fluxguardTeste.py
Adlib/funcoes.py
Adlib/importacao.py
Adlib/integracao.py
Adlib/libs.py
Adlib/logins.py
Adlib/robos.py
Adlib/utils.py
Adlib/virtaus.py
Adlib/webdriver/chromedriver
Adlib/webdriver/chromedriver.exe
LIB_ADTECH-3.9.11.dist-info/LICENSE
LIB_ADTECH-3.9.11.dist-info/METADATA
LIB_ADTECH-3.9.11.dist-info/WHEEL
LIB_ADTECH-3.9.11.dist-info/top_level.txt
LIB_ADTECH-3.9.11.dist-info/RECORD
