Metadata-Version: 2.2
Name: LIB_ADTECH
Version: 3.9.11
Summary: Melhorias para automação web
Home-page: https://github.com/DesenvolvimentoAD/Adlib
Author: Alan, Dannilo, Fabiano e Yan
Author-email: desenvolvimento@adpromotora.com.br
Classifier: Programming Language :: Python :: 3
Classifier: License :: OSI Approved :: MIT License
Classifier: Operating System :: OS Independent
Requires-Python: >=3.6
License-File: LICENSE
Dynamic: author
Dynamic: author-email
Dynamic: classifier
Dynamic: description
Dynamic: description-content-type
Dynamic: home-page
Dynamic: requires-python
Dynamic: summary
